{
  "version": 1,
  "generatedAt": "2026-04-11T21:31:20.897834+00:00",
  "singers": {
    "lim-young-woong": [
      "sHqFqWDviBg",
      "sFK89gemgKM",
      "30hZXHeB85U",
      "oQW9lY1ZAJA",
      "2WGc-5VdoGw",
      "xuexbvO29Gk",
      "ewk5MPptBIs",
      "ss7z2upAvX8",
      "tJut2wIsC1w",
      "jP2J0qnFtV4",
      "LKQ-18LoFQk",
      "TMfvkhkALbU"
    ],
    "lee-chan-won": [
      "G_m__AKDFKw",
      "yaeG5iPP414",
      "AIh7UA7UoYI",
      "AhmRaCQayv8",
      "68ShTNAwrLc",
      "wBnZWzQirdg",
      "pyk8uMgIXKY"
    ],
    "young-tak": [
      "cE65LD82Kkw",
      "fc-lKLdZf1Q",
      "GlVSW0TSm3Y"
    ],
    "song-ga-in": [
      "Cz_HTS8Sr2w",
      "EOrDQF6YdT8",
      "vtq4W8bp8B0"
    ],
    "na-hoon-a": [
      "NL2W7DKzZV4",
      "dQPlnJ6SYR0",
      "uGJoFdgE6ts",
      "usHvad89tbc",
      "IONYz6LNZgA",
      "MRrXRlVd0P0",
      "HU6RxqSEA2Y",
      "t77WNxrwvSU",
      "QElBrMTQXdo",
      "OmlAJV_XOM4"
    ],
    "joo-hyun-mi": [
      "siKZMFkIIwY"
    ],
    "jin-sung": [
      "tUn7A8otZIY"
    ],
    "jeong-dong-won": [
      "S0QU8-nKQnY",
      "t9rI88TTNzc",
      "RcJMPMH3sw8",
      "ymsc-Y19MTk",
      "RvnGjz9Z594"
    ],
    "hong-ja": [
      "uhFKZ_Tg4nY"
    ],
    "park-hyun-bin": [
      "LWY4UahvoXY"
    ],
    "hyun-cheol": [
      "VAb3sGdbbik",
      "1RRHPk4kr9g",
      "dGW6jKhpo5M",
      "Zj0U3QuPgKs",
      "3vni60bh-DA",
      "NmFxACudWCA",
      "iFYEI4ludAw",
      "pSRd79GCdmE",
      "dfXHOiFbpBI",
      "NCaMFHWsjC0",
      "NN_XlFpiVOU",
      "Qo5lrW5wxyw"
    ],
    "tae-jin-a": [
      "JbKmyUwu0EA",
      "rw9tFCiZrkA",
      "hdp08MbaT1E",
      "tlTNS3AlvQI",
      "H1eQYfUgFWg",
      "a40dV5l1O3g",
      "4uA-tgzLEI4",
      "_JGBTG-l-MI",
      "GwLsQgoE8sA",
      "GPWwk2nwog4",
      "UmJQmk36EEY",
      "gy7l2NNb_qI"
    ],
    "seol-un-do": [
      "xnKsDmx4HbM",
      "sqEI3eJ9OtM",
      "oM4cPK1VlXk",
      "A955KZkmlzk",
      "zk6PhLvDKCE",
      "AiRtNST8JV4",
      "ICwvMfJkobU",
      "FdYqePyNV4g",
      "EoUR-8Bq0l4",
      "RikgmODU33Y",
      "cGW8_zMPgHk",
      "NPHKlJIfXCg"
    ],
    "kim-heung-kook": [
      "FvRjJJG5RCE",
      "HhdZSe_lUBM",
      "zvZgDkfhW_o",
      "g2jg40DcdHs",
      "8p_N9hE9cNc",
      "XAY7Fw5pud0",
      "XeXi7G7Crlg",
      "7QHsA9GT7wo",
      "Z5u8cqxkDOE",
      "ieSNvZvKWTA",
      "GtcpKEJusNw",
      "Jp3srSY5N_Y"
    ],
    "nam-jin": [
      "1CDToG89XAE",
      "EHzneQaeH1Q",
      "PRR5uSvexlI",
      "6SvLf-2Qwks"
    ],
    "cho-yong-pil": [
      "kumMqZaEZf4",
      "_uYx13TPm-A",
      "VzVig1HuAYw",
      "CsGZEA3gCV8",
      "y6pccZYeuBY",
      "TzZBgUEX_QM",
      "SW2m_OGH4eU",
      "a6JUaK6Ssc4",
      "EA6PLfDueP0",
      "jvp_q3SIuvw",
      "s0VOftMC-yE",
      "h6VxAeVhO5s"
    ],
    "moon-hee-ok": [
      "XkfVkJ7Gay4",
      "2ttrjSk8JxU",
      "nULij_K0t24",
      "b2rjoe5wMRE",
      "WHsTwoeQgKQ",
      "5nvvWrX4o24",
      "VeMGClbFVEg",
      "YnUpxPCW5Gs",
      "fQ-hcuMgT9Y",
      "K0lzHQF-4gc",
      "_K6opyUx7kc",
      "PfxMnlHKzsU"
    ],
    "choi-jin-hee": [
      "nR8AJ1I5mac",
      "BVWzd661qu0",
      "0f0lqYnCUVQ",
      "wPZCs4Bv1rE",
      "u3NFDFN1FJU",
      "53SmkitPUo8",
      "2ysejwjm59Y",
      "atYW--38V0w",
      "bfbcKmqctG4",
      "X3w8Vg3sST4",
      "Gkgs6Z5XTMI",
      "YX1MZXjA1tY"
    ],
    "patti-kim": [
      "YqxwIB0-HOA",
      "FVw5grCWfPA",
      "uAZsjJX_e0E",
      "fXPOQGN2sME",
      "rEMJqz7V1_s",
      "1IoymubBdQE",
      "_QY-4qnoGeg",
      "K8tShoRSYqo",
      "KxsBeuXqnws",
      "5LaMRmKKaFY",
      "RVLwALjES84",
      "zcGTaWz1-PQ"
    ],
    "na-mi": [
      "4h4ZLDvpwOQ",
      "bbG8_Gg47-Q",
      "Vgjl6lEeBPc",
      "m7mE_03bqW8",
      "WRXjV3z-9O4",
      "InmwW-NB7j0",
      "Qo5ersmTuJ0",
      "hYQX26ZR1dM",
      "dsMP_VagYZ4",
      "GZkoJT1tW08",
      "KoPK3mghUXU",
      "nFQIdOj1fk8"
    ]
  },
  "categories": {
    "ballad": [
      "TGN0xJz7USk",
      "4VysJ-p6Olk",
      "kRhzvWQFdsQ"
    ],
    "upbeat": [
      "19oT04OuBhg"
    ],
    "latest": [
      "SocNxPCtjnY"
    ]
  },
  "playlists": {
    "top10-this-week": [
      "eXMR3e8SsiQ",
      "SocNxPCtjnY"
    ],
    "bedtime": [
      "19oT04OuBhg"
    ],
    "drive": [
      "moVgOwYOXec"
    ],
    "morning": [
      "wBnZWzQirdg"
    ]
  }
}